MANIFEST.in
setup.py
startOpenElectrophy.py
OpenElectrophy/__init__.py
OpenElectrophy/version.py
OpenElectrophy.egg-info/PKG-INFO
OpenElectrophy.egg-info/SOURCES.txt
OpenElectrophy.egg-info/dependency_links.txt
OpenElectrophy.egg-info/requires.txt
OpenElectrophy.egg-info/top_level.txt
OpenElectrophy/core/__init__.py
OpenElectrophy/core/base.py
OpenElectrophy/core/classes.py
OpenElectrophy/core/imagemask.py
OpenElectrophy/core/imageserie.py
OpenElectrophy/core/licktrain.py
OpenElectrophy/core/oscillation.py
OpenElectrophy/core/respirationsignal.py
OpenElectrophy/core/sqlmapper.py
OpenElectrophy/core/tools.py
OpenElectrophy/gui/__init__.py
OpenElectrophy/gui/contextmenu.py
OpenElectrophy/gui/createdb.py
OpenElectrophy/gui/editdb.py
OpenElectrophy/gui/explorer.py
OpenElectrophy/gui/importdata.py
OpenElectrophy/gui/mainwindow.py
OpenElectrophy/gui/opendb.py
OpenElectrophy/gui/qt.py
OpenElectrophy/gui/qtsqltreeview.py
OpenElectrophy/gui/schemadesign.py
OpenElectrophy/gui/viewdesigner.py
OpenElectrophy/gui/guiutil/__init__.py
OpenElectrophy/gui/guiutil/myguidata.py
OpenElectrophy/gui/guiutil/mymatplotlib.py
OpenElectrophy/gui/guiutil/mypyqtgraph.py
OpenElectrophy/gui/guiutil/picklesettings.py
OpenElectrophy/gui/guiutil/resthtml.py
OpenElectrophy/gui/guiutil/icons/__init__.py
OpenElectrophy/gui/guiutil/icons/icons.py
OpenElectrophy/gui/guiutil/icons/icons_py3.py
OpenElectrophy/gui/guiutil/icons/make_ressources.py
OpenElectrophy/gui/guiutil/icons/test_ressources.py
OpenElectrophy/gui/oscillationdetection/__init__.py
OpenElectrophy/gui/oscillationdetection/oscillationdetection.py
OpenElectrophy/gui/spikesorting/__init__.py
OpenElectrophy/gui/spikesorting/base.py
OpenElectrophy/gui/spikesorting/features.py
OpenElectrophy/gui/spikesorting/lists.py
OpenElectrophy/gui/spikesorting/lists_old.py
OpenElectrophy/gui/spikesorting/misc.py
OpenElectrophy/gui/spikesorting/ndviewer.py
OpenElectrophy/gui/spikesorting/signals.py
OpenElectrophy/gui/spikesorting/spikesortingwidgets.py
OpenElectrophy/gui/spikesorting/spikesortingwindow.py
OpenElectrophy/gui/spikesorting/toolchain.py
OpenElectrophy/gui/spikesorting/waveforms.py
OpenElectrophy/gui/viewers/__init__.py
