Metadata-Version: 1.1
Name: OpenElectrophy
Version: 0.3.6
Summary: OpenElectrophy : an electrophysiological data- and analysis-sharing framework
Home-page: http://packages.python.org/OpenElectrophy/
Author: Samuel Garcia
Author-email: sam.garcia.die@gmail.com
License: BSD
Platform: UNKNOWN
Classifier: Development Status :: 3 - Alpha
Classifier: Intended Audience :: Science/Research
Classifier: License :: OSI Approved :: BSD License
Classifier: Natural Language :: English
Classifier: Operating System :: OS Independent
Classifier: Topic :: Scientific/Engineering :: Bio-Informatics
Classifier: Programming Language :: Python :: 2
